{"data":{"items":{"2025-5-01":{"mittag":{"type":"mittag","chef":"Ute","menu":"gemischter Salat, Blumenkohl gebacken, Kartoffelbrei"},"abend":{"type":"abend","chef":"Wolfgang","menu":"Süßkartoffeleintopf mit weißen Bohnen, Fladenbrot, Aufstrich"}},"2025-5-02":{"mittag":{"type":"mittag","chef":"Chris + Wolfgang","menu":"gemischter Salat, indisches Curry mit Weißkohl, Tomatendal, Basmatireis, Nachtisch"},"abend":{"type":"abend","chef":"Wolfgang","menu":"Salat, Gemüseeintopf mit Tofu, Aufstrich, Brot"}},"2025-5-03":{"mittag":{"type":"mittag","chef":"Ute Mittagessen + Chris Abendessen","menu":"Rohkostsalat, orientalisches Ofengemüse, Hummus"},"abend":{"type":"abend","chef":"Eu wärmt auf","menu":"gemischter Salat, Ratatouille, Reis"}},"2025-5-04":{"mittag":{"type":"mittag","chef":"Ute, Jürgen wärmt auf","menu":"gemischter Salat, Fenchel gratiniert, Lauchsauce, Ofenkartoffeln, Nachtisch"},"abend":{"type":"abend","menu":"Linseneintopf"}}},"generatedAt":"2025-05-02T20:02:50.674Z","warnings":[]}}